hypixelpyplus/__init__.py
hypixelpyplus/hypixelpyplus.py
hypixelpyplus-0.1.2.dist-info/METADATA
hypixelpyplus-0.1.2.dist-info/WHEEL
hypixelpyplus-0.1.2.dist-info/top_level.txt
hypixelpyplus-0.1.2.dist-info/RECORD
