Metadata-Version: 2.4
Name: hypixelpyplus
Version: 0.1.2
Summary: An unofficial Python wrapper for the Hypixel API
License: MIT
Requires-Python: >=3.7
Requires-Dist: requests
